WeatherUnits/__init__.py
WeatherUnits/__init__.pyo
WeatherUnits/airQuality/__init__.py
WeatherUnits/airQuality/__init__.pyo
WeatherUnits/base/Decorators.py
WeatherUnits/base/Decorators.pyo
WeatherUnits/base/SmartBases.py
WeatherUnits/base/_Measurement.py
WeatherUnits/base/_Measurement.pyo
WeatherUnits/base/_ScalingMeasurement.py
WeatherUnits/base/_ScalingMeasurement.pyo
WeatherUnits/base/_SmartFloat.py
WeatherUnits/base/_SmartFloat.pyo
WeatherUnits/base/__init__.py
WeatherUnits/base/__init__.pyo
WeatherUnits/config/__init__.py
WeatherUnits/config/__init__.pyo
WeatherUnits/config/si.ini
WeatherUnits/config/template.ini
WeatherUnits/config/us.ini
WeatherUnits/defaults/WeatherFlow/__init__.py
WeatherUnits/defaults/__init__.py
WeatherUnits/derived/__init__.py
WeatherUnits/derived/__init__.pyo
WeatherUnits/derived/density.py
WeatherUnits/derived/density.pyo
WeatherUnits/derived/partsPer.py
WeatherUnits/derived/partsPer.pyo
WeatherUnits/derived/precipitation.py
WeatherUnits/derived/precipitation.pyo
WeatherUnits/derived/rate.py
WeatherUnits/derived/rate.pyo
WeatherUnits/derived/volume.py
WeatherUnits/derived/volume.pyo
WeatherUnits/derived/wind.py
WeatherUnits/derived/wind.pyo
WeatherUnits/digital/__init__.py
WeatherUnits/digital/__init__.pyo
WeatherUnits/errors/Conversion.py
WeatherUnits/errors/Conversion.pyo
WeatherUnits/errors/Unit.py
WeatherUnits/errors/Unit.pyo
WeatherUnits/errors/__init__.py
WeatherUnits/errors/__init__.pyo
WeatherUnits/length/__init__.py
WeatherUnits/length/__init__.pyo
WeatherUnits/length/imperial.py
WeatherUnits/length/imperial.pyo
WeatherUnits/length/length.py
WeatherUnits/length/length.pyo
WeatherUnits/length/metric.py
WeatherUnits/length/metric.pyo
WeatherUnits/mass/__init__.py
WeatherUnits/mass/__init__.pyo
WeatherUnits/mass/imperial.py
WeatherUnits/mass/imperial.pyo
WeatherUnits/mass/mass.py
WeatherUnits/mass/mass.pyo
WeatherUnits/mass/metric.py
WeatherUnits/mass/metric.pyo
WeatherUnits/others/__init__.py
WeatherUnits/others/__init__.pyo
weatherunits-0.7.1.dist-info/LICENSE.txt
weatherunits-0.7.1.dist-info/WHEEL
weatherunits-0.7.1.dist-info/METADATA
weatherunits-0.7.1.dist-info/RECORD
