Metadata-Version: 2.1
Name: weatherunits
Version: 0.7.1
Summary: Easy conversion for common units
Home-page: https://github.com/noblecloud/WeatherUnits
License: MIT
Keywords: weather,units,temperature,conversion,converter
Author: noblecloud
Author-email: git@noblecloud.io
Requires-Python: >=3.10,<4.0
Classifier: Development Status :: 4 - Beta
Classifier: Intended Audience :: Developers
Classifier: Intended Audience :: Education
Classifier: Intended Audience :: Science/Research
Classifier: License :: OSI Approved :: MIT License
Classifier: Natural Language :: English
Classifier: Operating System :: OS Independent
Classifier: Programming Language :: Python :: 3
Classifier: Programming Language :: Python :: 3.10
Classifier: Programming Language :: Python :: 3.11
Classifier: Programming Language :: Python :: 3.10
Classifier: Topic :: Scientific/Engineering :: Atmospheric Science
Classifier: Topic :: Scientific/Engineering :: Physics
Classifier: Topic :: Software Development :: Libraries
Classifier: Topic :: Software Development :: Libraries :: Python Modules
Classifier: Topic :: Utilities
Project-URL: Bug Tracker, https://github.com/noblecloud/WeatherUnits/issues
Project-URL: Repository, https://github.com/noblecloud/WeatherUnits
